odoo8_addon_partner_default_sale_discount-8.0.1.0.0.99.dev2-nspkg.pth
odoo_addons/partner_default_sale_discount/README.rst
odoo_addons/partner_default_sale_discount/__init__.py
odoo_addons/partner_default_sale_discount/__openerp__.py
odoo_addons/partner_default_sale_discount/i18n/am.po
odoo_addons/partner_default_sale_discount/i18n/ar.po
odoo_addons/partner_default_sale_discount/i18n/bg.po
odoo_addons/partner_default_sale_discount/i18n/bs.po
odoo_addons/partner_default_sale_discount/i18n/ca.po
odoo_addons/partner_default_sale_discount/i18n/cs.po
odoo_addons/partner_default_sale_discount/i18n/da.po
odoo_addons/partner_default_sale_discount/i18n/de.po
odoo_addons/partner_default_sale_discount/i18n/el_GR.po
odoo_addons/partner_default_sale_discount/i18n/en_GB.po
odoo_addons/partner_default_sale_discount/i18n/es.po
odoo_addons/partner_default_sale_discount/i18n/es_CR.po
odoo_addons/partner_default_sale_discount/i18n/es_EC.po
odoo_addons/partner_default_sale_discount/i18n/es_ES.po
odoo_addons/partner_default_sale_discount/i18n/es_MX.po
odoo_addons/partner_default_sale_discount/i18n/es_VE.po
odoo_addons/partner_default_sale_discount/i18n/et.po
odoo_addons/partner_default_sale_discount/i18n/eu.po
odoo_addons/partner_default_sale_discount/i18n/fi.po
odoo_addons/partner_default_sale_discount/i18n/fr.po
odoo_addons/partner_default_sale_discount/i18n/fr_CA.po
odoo_addons/partner_default_sale_discount/i18n/fr_CH.po
odoo_addons/partner_default_sale_discount/i18n/gl.po
odoo_addons/partner_default_sale_discount/i18n/hr.po
odoo_addons/partner_default_sale_discount/i18n/hr_HR.po
odoo_addons/partner_default_sale_discount/i18n/hu.po
odoo_addons/partner_default_sale_discount/i18n/it.po
odoo_addons/partner_default_sale_discount/i18n/ja.po
odoo_addons/partner_default_sale_discount/i18n/lt.po
odoo_addons/partner_default_sale_discount/i18n/lv.po
odoo_addons/partner_default_sale_discount/i18n/mk.po
odoo_addons/partner_default_sale_discount/i18n/mn.po
odoo8_addon_partner_default_sale_discount-8.0.1.0.0.99.dev2.dist-info/METADATA
odoo8_addon_partner_default_sale_discount-8.0.1.0.0.99.dev2.dist-info/WHEEL
odoo8_addon_partner_default_sale_discount-8.0.1.0.0.99.dev2.dist-info/namespace_packages.txt
odoo8_addon_partner_default_sale_discount-8.0.1.0.0.99.dev2.dist-info/top_level.txt
odoo8_addon_partner_default_sale_discount-8.0.1.0.0.99.dev2.dist-info/RECORD
